README.txt
setup.cfg
setup.py
collective/__init__.py
collective.portlet.paypal.egg-info/PKG-INFO
collective.portlet.paypal.egg-info/SOURCES.txt
collective.portlet.paypal.egg-info/dependency_links.txt
collective.portlet.paypal.egg-info/entry_points.txt
collective.portlet.paypal.egg-info/namespace_packages.txt
collective.portlet.paypal.egg-info/not-zip-safe
collective.portlet.paypal.egg-info/requires.txt
collective.portlet.paypal.egg-info/top_level.txt
collective/portlet/__init__.py
collective/portlet/paypal/__init__.py
collective/portlet/paypal/configure.zcml
collective/portlet/paypal/paypalportlet.pt
collective/portlet/paypal/paypalportlet.py
collective/portlet/paypal/version.txt
collective/portlet/paypal/profiles/default/portlets.xml
collective/portlet/paypal/tests/__init__.py
collective/portlet/paypal/tests/base.py
collective/portlet/paypal/tests/test_portlet.py
docs/HISTORY.txt
docs/INSTALL.txt
docs/LICENSE.GPL
docs/LICENSE.txt
