Metadata-Version: 1.0
Name: collective.portlet.paypal
Version: 0.2dev-r57320
Summary: This portlet shows a button that allows a site owner to collect donations through PayPal.
Home-page: http://www.speedbreeze.com
Author: Jonathan Wilde
Author-email: plone-developers@lists.sourceforge.net
License: GPL
Keywords: web zope plone portlet
Platform: UNKNOWN
Classifier: Framework :: Plone
Classifier: Framework :: Zope2
Classifier: Framework :: Zope3
Classifier: Programming Language :: Python
Classifier: Topic :: Software Development :: Libraries :: Python Modules
